Metadata-Version: 2.0
Name: valer.core.listing
Version: 1.5.3rc11
Summary: ReactJS powered listing tables for SENAITE LIMS
Home-page: https://github.com/valeriozhang/senaite.core.listing
Author: Valer Group LLC
Author-email: valerio.zhang@valer.us
License: GPLv2
Keywords: senaite,lims,opensource,reactjs
Platform: UNKNOWN
Classifier: Programming Language :: Python
Classifier: Framework :: Plone
Classifier: Framework :: Zope2
Provides-Extra: test
Requires-Dist: setuptools
Requires-Dist: valer.core (>=1.3.5rc11)
Provides-Extra: test
Requires-Dist: Products.PloneTestCase; extra == 'test'
Requires-Dist: plone.app.testing; extra == 'test'
Requires-Dist: unittest2; extra == 'test'
